setup.py
abacba/__init__.py
abacba.egg-info/PKG-INFO
abacba.egg-info/SOURCES.txt
abacba.egg-info/dependency_links.txt
abacba.egg-info/requires.txt
abacba.egg-info/top_level.txt